lsmeta_pydash/__init__.py
lsmeta_pydash-1.0.0.dist-info/METADATA
lsmeta_pydash-1.0.0.dist-info/WHEEL
lsmeta_pydash-1.0.0.dist-info/RECORD
