Metadata-Version: 2.1
Name: lsmeta-pydash
Version: 1.0.0
Summary: Meta package for pydash
Author: Your Name
Author-email: you@example.com
Requires-Python: >=3.11,<4.0
Classifier: Programming Language :: Python :: 3
Classifier: Programming Language :: Python :: 3.11
Requires-Dist: pydash (>=7.0.6,<8.0.0)
